pine/__init__.py
pine/__main__.py
pine/pine.py
pine/cli/__init__.py
pine/cli/banner.py
pine/cli/cli.py
pine/error/__init__.py
pine/items/__init__.py
pine/items/base.py
pine/items/html.py
pine/items/list.py
pine/items/tags.py
pine/items/text.py
pine/pinelib/__init__.py
pine/pinelib/source.py
pine/pineparser/__init__.py
pine/pineparser/base.py
pine/pineparser/pineparser.py
pine_md-0.1.2.data/data/md_data/.pine-config.json
pine_md-0.1.2.data/scripts/pine
pine_md-0.1.2.dist-info/LICENSE
pine_md-0.1.2.dist-info/METADATA
pine_md-0.1.2.dist-info/WHEEL
pine_md-0.1.2.dist-info/entry_points.txt
pine_md-0.1.2.dist-info/top_level.txt
pine_md-0.1.2.dist-info/RECORD
