Metadata-Version: 2.1
Name: pine-md
Version: 0.1.2
Summary: Pine Markdown: An acid markdown flavour.
Home-page: https://github.com/pedromxavier/pine-md
Author: Pedro Maciel Xavier
Author-email: pedromxavier@poli.ufrj.br
License: UNKNOWN
Project-URL: Bug Tracker, https://github.com/pedromxavier/pine-md/issues
Project-URL: Source, https://github.com/pedromxavier/pine-md
Platform: UNKNOWN
Classifier: Programming Language :: Python :: 3
Requires-Python: <4,>=3.7
Requires-Dist: argparse
Requires-Dist: pyckage (>=0.1.1)
Requires-Dist: cstream (>=1.0.0)
Requires-Dist: ply (>=3.11.0)
